{
  "type": "starry_skies:simple",
  "config": {
    "block": "byg:brimstone",

    "size": {
      "type": "minecraft:uniform",
      "min_inclusive": 5,
      "max_exclusive": 12
    },

    "decorators": {
      "starry_skies:mod_compat/byg/boric_fire": 0.75
    },
    "spawns": [],
    "generation": {
      "weight": 0.5,
      "group": "starry_skies:nether/decorative"
    }
  },
  "fabric:load_conditions": [
    {
      "condition": "fabric:all_mods_loaded",
      "values": [
        "byg"
      ]
    }
  ]
}
