{
  "type": "starry_skies:core",
  "config": {
    "core_block": "%starry_skies:manganese_ore",
    "shell_block": "$starry_skies:stones",
    "core_radius": {
      "min_inclusive": 4,
      "max_exclusive": 6
    },

    "size": {
      "type": "minecraft:uniform",
      "min_inclusive": 8,
      "max_exclusive": 10
    },

    "decorators": {},
    "spawns": [],
    "fabric:load_conditions": [
      {
        condition=starry_skies: unique_block_group_exist,
        values=System.Object
      []
      }
    ],
    "generation": {
      "weight": 0.9,
      "group": "starry_skies:overworld/ores"
    }
  }
}
