{
  "type": "starry_skies:core",
  "config": {
    "core_block": "%starry_skies:nikolite_ore",
    "min_core_size": 3,
    "max_core_size": 5,
    "main_block": "$starry_skies:stones",

    "size": {
      "type": "minecraft:uniform",
      "min_inclusive": 6,
      "max_exclusive": 8
    },

    "decorators": {},
    "spawns": [],
    "fabric:load_conditions": [
      {
        condition=starry_skies: unique_block_group_exist,
        values=System.Object
      []
      }
    ],
    "generation": {
      "weight": 1.0,
      "group": "starry_skies:overworld/ores"
    }
  }
}
