{
  "type": "starry_skies:mushroom",
  "config": {
    "decorators": {},
    "spawns": [
      {
        "type": "minecraft:mooshroom",
        "chance": 0.25,
        "min_count": 1,
        "max_count": 3
      }
    ],
    "size": {
      "type": "minecraft:uniform",
      "min_inclusive": 4,
      "max_exclusive": 8
    },
    "mushroom_block": "minecraft:brown_mushroom_block",
    "stem_block": "minecraft:mushroom_stem",
    "min_shell_size": 2,
    "max_shell_size": 3,

    "generation": {
      "weight": 1.0,
      "group": "starry_skies:overworld/treasure"
    }
  }
}
